patrix/__init__.py
patrix/radix.py
patrix/trie.py
patrix-0.3.0.dist-info/licenses/LICENSE.txt
patrix-0.3.0.dist-info/METADATA
patrix-0.3.0.dist-info/WHEEL
patrix-0.3.0.dist-info/top_level.txt
patrix-0.3.0.dist-info/RECORD
