Metadata-Version: 2.4
Name: patrix
Version: 0.3.0
Summary: A python package that uses a compressed prefix tree (radix tree) to store a dictionary of known words and suggests completions for partial entries.
Author-email: Martin Beroiz <martin.beroiz@ligo.org>
License: MIT
Project-URL: Homepage, https://patrix.readthedocs.io/
Project-URL: Repository, https://github.com/martinberoiz/patrix
Project-URL: Documentation, https://patrix.readthedocs.io/
Keywords: autocomplete,radix,trie,prefix-tree,compressed-trie,patricia-tree,search,completion,suggestions,dictionary,prefix-matching
Classifier: License :: OSI Approved :: MIT License
Classifier: Programming Language :: Python :: 3
Classifier: Programming Language :: Python :: 3.10
Classifier: Programming Language :: Python :: 3.11
Classifier: Programming Language :: Python :: 3.12
Classifier: Programming Language :: Python :: 3.13
Classifier: Programming Language :: Python :: 3.14
Requires-Python: >=3.10
License-File: LICENSE.txt
Dynamic: license-file
